coursera/__init__.py
coursera/api.py
coursera/commandline.py
coursera/cookies.py
coursera/coursera_dl.py
coursera/credentials.py
coursera/define.py
coursera/downloaders.py
coursera/extractors.py
coursera/filtering.py
coursera/formatting.py
coursera/network.py
coursera/parallel.py
coursera/playlist.py
coursera/py2devtools.py
coursera/sampler.py
coursera/utils.py
coursera/workflow.py
coursera_dl-0.11.5.dist-info/AUTHORS.md
coursera_dl-0.11.5.dist-info/LICENSE
coursera_dl-0.11.5.dist-info/METADATA
coursera_dl-0.11.5.dist-info/WHEEL
coursera_dl-0.11.5.dist-info/entry_points.txt
coursera_dl-0.11.5.dist-info/top_level.txt
coursera_dl-0.11.5.dist-info/RECORD
