Metadata-Version: 2.1
Name: coursera-dl
Version: 0.11.5
Summary: Script for downloading Coursera.org videos and naming them.
Home-page: https://github.com/coursera-dl/coursera-dl
Maintainer: Rogério Theodoro de Brito
Maintainer-email: rbrito@ime.usp.br
License: LGPL
Keywords: coursera-dl,coursera,download,education,MOOCs,video
Platform: any
Classifier: Development Status :: 4 - Beta
Classifier: Environment :: Console
Classifier: Intended Audience :: End Users/Desktop
Classifier: License :: OSI Approved :: GNU Lesser General Public License v3 or later (LGPLv3+)
Classifier: Operating System :: OS Independent
Classifier: Programming Language :: Python :: 2
Classifier: Programming Language :: Python :: 2.7
Classifier: Programming Language :: Python :: 3
Classifier: Programming Language :: Python :: 3.4
Classifier: Programming Language :: Python :: 3.5
Classifier: Programming Language :: Python :: 3.6
Classifier: Programming Language :: Python :: Implementation :: CPython
Classifier: Programming Language :: Python :: Implementation :: PyPy
Classifier: Programming Language :: Python
Classifier: Topic :: Education
Requires-Dist: beautifulsoup4 (>=4.1.3)
Requires-Dist: requests (>=2.10.0)
Requires-Dist: six (>=1.5.0)
Requires-Dist: urllib3 (>=1.23)
Requires-Dist: pyasn1 (>=0.1.7)
Requires-Dist: keyring (>=4.0)
Requires-Dist: configargparse (>=0.12.0)
Requires-Dist: attrs (==18.1.0)
Provides-Extra: dev
Requires-Dist: pytest ; extra == 'dev'
Requires-Dist: pytest-cov ; extra == 'dev'
Requires-Dist: pytest-xdist ; extra == 'dev'
Requires-Dist: mock (>=1.0.1) ; extra == 'dev'
Requires-Dist: coverage (>=3.7) ; extra == 'dev'
Requires-Dist: keyrings.alt ; extra == 'dev'
Requires-Dist: tox ; extra == 'dev'
